collective.cover-3.0.0-nspkg.pth
collective/cover/__init__.py
collective/cover/config.py
collective/cover/configure.zcml
collective/cover/content.py
collective/cover/controlpanel.py
collective/cover/grids.py
collective/cover/grids.zcml
collective/cover/interfaces.py
collective/cover/logger.py
collective/cover/permissions.zcml
collective/cover/profiles.zcml
collective/cover/setuphandlers.py
collective/cover/subscribers.py
collective/cover/subscribers.zcml
collective/cover/testing.py
collective/cover/utils.py
collective/cover/vocabularies.py
collective/cover/vocabularies.zcml
collective/cover/behaviors/__init__.py
collective/cover/behaviors/configure.zcml
collective/cover/behaviors/interfaces.py
collective/cover/browser/__init__.py
collective/cover/browser/compose.py
collective/cover/browser/configure.zcml
collective/cover/browser/contentchooser.py
collective/cover/browser/cover.py
collective/cover/browser/layout.py
collective/cover/browser/layoutpolicy.py
collective/cover/browser/scaling.py
collective/cover/browser/static/README.rst
collective/cover/browser/static/cover-8c2bf03.css
collective/cover/browser/static/cover-8c2bf03.js
collective/cover/browser/static/icons-8c2bf03.css
collective/cover/browser/static/icons-8c2bf03.js
collective/cover/browser/static/icons.pt
collective/cover/browser/static/resources.pt
collective/cover/browser/static/_/icons/fonts/cover-icons.eot
collective/cover/browser/static/_/icons/fonts/cover-icons.svg
collective/cover/browser/static/_/icons/fonts/cover-icons.ttf
collective/cover/browser/static/_/icons/fonts/cover-icons.woff
collective/cover/browser/static/galleria/theme.css
collective/cover/browser/static/galleria/theme.js
collective/cover/browser/static/img/arrow-left.gif
collective/cover/browser/static/img/arrow-right.gif
collective/cover/browser/static/img/columns.png
collective/cover/browser/static/img/conf.png
collective/cover/browser/static/img/dot.png
collective/cover/browser/static/img/drophere.png
collective.cover-3.0.0.dist-info/METADATA
collective.cover-3.0.0.dist-info/WHEEL
collective.cover-3.0.0.dist-info/entry_points.txt
collective.cover-3.0.0.dist-info/namespace_packages.txt
collective.cover-3.0.0.dist-info/top_level.txt
collective.cover-3.0.0.dist-info/RECORD
