Metadata-Version: 2.1
Name: collective.cover
Version: 3.0.0
Summary: A sane, working, editor-friendly way of creating front pages and other composite pages. Working now, for mere mortals.
Home-page: https://github.com/collective/collective.cover
Author: Carlos de la Guardia et al.
Author-email: cguardia@yahoo.com
License: GPLv2
Project-URL: PyPI, https://pypi.python.org/pypi/collective.cover
Project-URL: Source, https://github.com/collective/collective.cover
Project-URL: Tracker, https://github.com/collective/collective.cover/issues
Keywords: plone cover javascript dexterity
Platform: UNKNOWN
Classifier: Development Status :: 5 - Production/Stable
Classifier: Environment :: Web Environment
Classifier: Framework :: Plone
Classifier: Framework :: Plone :: 5.2
Classifier: Intended Audience :: End Users/Desktop
Classifier: Intended Audience :: System Administrators
Classifier: License :: OSI Approved :: GNU General Public License v2 (GPLv2)
Classifier: Operating System :: OS Independent
Classifier: Programming Language :: JavaScript
Classifier: Programming Language :: Python
Classifier: Programming Language :: Python :: 2.7
Classifier: Programming Language :: Python :: 3
Classifier: Programming Language :: Python :: 3.7
Classifier: Programming Language :: Python :: 3.8
Classifier: Topic :: Office/Business :: News/Diary
Classifier: Topic :: Software Development :: Libraries :: Python Modules
Requires-Python: >=2.7,!=3.0.*,!=3.1.*,!=3.2.*,!=3.3.*,!=3.4.*,!=3.5.*,!=3.6.*
Requires-Dist: AccessControl
Requires-Dist: Acquisition
Requires-Dist: Missing
Requires-Dist: Products.CMFCore
Requires-Dist: Products.CMFPlone (>=5.2)
Requires-Dist: Products.GenericSetup
Requires-Dist: Products.MimetypesRegistry
Requires-Dist: Products.ZCatalog
Requires-Dist: ZODB
Requires-Dist: Zope
Requires-Dist: collective.js.bootstrap
Requires-Dist: collective.js.galleria
Requires-Dist: collective.js.jqueryui
Requires-Dist: persistent
Requires-Dist: plone.api
Requires-Dist: plone.app.blocks
Requires-Dist: plone.app.contentmenu
Requires-Dist: plone.app.dexterity
Requires-Dist: plone.app.iterate
Requires-Dist: plone.app.jquerytools
Requires-Dist: plone.app.layout
Requires-Dist: plone.app.linkintegrity
Requires-Dist: plone.app.lockingbehavior
Requires-Dist: plone.app.registry
Requires-Dist: plone.app.textfield
Requires-Dist: plone.app.tiles
Requires-Dist: plone.app.uuid
Requires-Dist: plone.app.vocabularies
Requires-Dist: plone.autoform
Requires-Dist: plone.behavior
Requires-Dist: plone.dexterity
Requires-Dist: plone.i18n
Requires-Dist: plone.indexer
Requires-Dist: plone.locking
Requires-Dist: plone.memoize
Requires-Dist: plone.namedfile
Requires-Dist: plone.registry
Requires-Dist: plone.rfc822
Requires-Dist: plone.scale
Requires-Dist: plone.supermodel
Requires-Dist: plone.tiles
Requires-Dist: plone.uuid
Requires-Dist: plone.z3cform
Requires-Dist: setuptools
Requires-Dist: six
Requires-Dist: z3c.caching
Requires-Dist: z3c.form
Requires-Dist: z3c.relationfield
Requires-Dist: zExceptions
Requires-Dist: zope.annotation
Requires-Dist: zope.browserpage
Requires-Dist: zope.component
Requires-Dist: zope.container
Requires-Dist: zope.event
Requires-Dist: zope.i18nmessageid
Requires-Dist: zope.interface
Requires-Dist: zope.intid
Requires-Dist: zope.lifecycleevent
Requires-Dist: zope.publisher
Requires-Dist: zope.schema
Requires-Dist: zope.traversing
Provides-Extra: relations
Requires-Dist: plone.app.dexterity[relations] ; extra == 'relations'
Provides-Extra: test
Requires-Dist: lxml ; extra == 'test'
Requires-Dist: mock ; extra == 'test'
Requires-Dist: plone.api ; extra == 'test'
Requires-Dist: plone.app.robotframework ; extra == 'test'
Requires-Dist: plone.app.testing[robot] ; extra == 'test'
Requires-Dist: plone.browserlayer ; extra == 'test'
Requires-Dist: plone.cachepurging ; extra == 'test'
Requires-Dist: plone.testing ; extra == 'test'
Requires-Dist: robotsuite ; extra == 'test'
